odoo/addons/hotel_housekeeping/.copier-answers.yml
odoo/addons/hotel_housekeeping/.editorconfig
odoo/addons/hotel_housekeeping/.eslintrc.yml
odoo/addons/hotel_housekeeping/.flake8
odoo/addons/hotel_housekeeping/.gitignore
odoo/addons/hotel_housekeeping/.isort.cfg
odoo/addons/hotel_housekeeping/.pre-commit-config.yaml
odoo/addons/hotel_housekeeping/.prettierrc.yml
odoo/addons/hotel_housekeeping/.pylintrc
odoo/addons/hotel_housekeeping/.pylintrc-mandatory
odoo/addons/hotel_housekeeping/README.rst
odoo/addons/hotel_housekeeping/__init__.py
odoo/addons/hotel_housekeeping/__manifest__.py
odoo/addons/hotel_housekeeping/.github/workflows/pre-commit.yml
odoo/addons/hotel_housekeeping/.github/workflows/stale.yml
odoo/addons/hotel_housekeeping/.github/workflows/test.yml
odoo/addons/hotel_housekeeping/demo/hotel_housekeeping_data.xml
odoo/addons/hotel_housekeeping/i18n/es.po
odoo/addons/hotel_housekeeping/i18n/fr.po
odoo/addons/hotel_housekeeping/i18n/fr_BE.po
odoo/addons/hotel_housekeeping/i18n/hotel_housekeeping.pot
odoo/addons/hotel_housekeeping/i18n/it.po
odoo/addons/hotel_housekeeping/i18n/sv.po
odoo/addons/hotel_housekeeping/models/__init__.py
odoo/addons/hotel_housekeeping/models/hotel_activity.py
odoo/addons/hotel_housekeeping/models/hotel_housekeeping.py
odoo/addons/hotel_housekeeping/models/hotel_housekeeping_activities.py
odoo/addons/hotel_housekeeping/models/hotel_housekeeping_activity_type.py
odoo/addons/hotel_housekeeping/readme/CONTRIBUTORS.rst
odoo/addons/hotel_housekeeping/readme/DESCRIPTION.rst
odoo/addons/hotel_housekeeping/report/__init__.py
odoo/addons/hotel_housekeeping/report/hotel_housekeeping_report.xml
odoo/addons/hotel_housekeeping/report/housekeeping_report.py
odoo/addons/hotel_housekeeping/security/ir.model.access.csv
odoo/addons/hotel_housekeeping/static/description/icon.png
odoo/addons/hotel_housekeeping/static/description/index.html
odoo/addons/hotel_housekeeping/static/description/serpent.png
odoo/addons/hotel_housekeeping/tests/__init__.py
odoo_addon_hotel_housekeeping-16.0.1.0.0.10.dist-info/METADATA
odoo_addon_hotel_housekeeping-16.0.1.0.0.10.dist-info/WHEEL
odoo_addon_hotel_housekeeping-16.0.1.0.0.10.dist-info/top_level.txt
odoo_addon_hotel_housekeeping-16.0.1.0.0.10.dist-info/RECORD
