Metadata-Version: 2.1
Name: odoo-addon-hotel_housekeeping
Version: 16.0.1.0.0.10
Summary: Manages Housekeeping Activities and its Process
Home-page: https://github.com/OCA/vertical-hotel
Author: Odoo Community Association (OCA), Serpent Consulting Services Pvt. Ltd., Odoo S.A.
Author-email: support@odoo-community.org
License: AGPL-3
Classifier: Programming Language :: Python
Classifier: Framework :: Odoo
Classifier: Framework :: Odoo :: 16.0
Classifier: License :: OSI Approved :: GNU Affero General Public License v3
Requires-Python: >=3.10
Requires-Dist: odoo-addon-hotel<16.1dev,>=16.0dev
Requires-Dist: odoo<16.1dev,>=16.0a
